yp_dl/__init__.py
yp_dl/exceptions.py
yp_dl/yp_dl.py
yp_dl-0.9.19.dist-info/METADATA
yp_dl-0.9.19.dist-info/WHEEL
yp_dl-0.9.19.dist-info/entry_points.txt
yp_dl-0.9.19.dist-info/licenses/LICENSE
yp_dl-0.9.19.dist-info/RECORD
