Metadata-Version: 2.4
Name: yp-dl
Version: 0.9.19
Summary: Asynchronous scraper to download youtube community posts
License: MIT
License-File: LICENSE
Author: Boltzmann Potato
Author-email: boltzmannpotato@proton.me
Requires-Python: >=3.11,<4.0
Classifier: License :: OSI Approved :: MIT License
Classifier: Programming Language :: Python :: 3
Classifier: Programming Language :: Python :: 3.11
Classifier: Programming Language :: Python :: 3.12
Classifier: Programming Language :: Python :: 3.13
Classifier: Programming Language :: Python :: 3.14
Requires-Dist: lxml (>=6.0.2,<7.0.0)
Requires-Dist: lxml-html-clean (>=0.4.1,<0.5.0)
Requires-Dist: requests-html (>=0.10.0,<0.11.0)
Requires-Dist: rich (>=13.6.0,<14.0.0)
